MANIFEST.in
README.txt
setup.py
eliwog/Common.py
eliwog/Const.py
eliwog/CurrencyRouletteGame.py
eliwog/Game.py
eliwog/GameManager.py
eliwog/GuessGame.py
eliwog/Live.py
eliwog/MainGame.py
eliwog/MainScores.py
eliwog/MemoryGame.py
eliwog/Score.py
eliwog/__init__.py
eliwog.egg-info/PKG-INFO
eliwog.egg-info/SOURCES.txt
eliwog.egg-info/dependency_links.txt
eliwog.egg-info/requires.txt
eliwog.egg-info/top_level.txt
eliwog/templates/__init__.py
eliwog/templates/error.html
eliwog/templates/index.html